tests/__init__.py
tests/test_search.py
tests/test_upload.py
weaver/__init__.py
weaver/app.py
weaver/config.py
weaver/version.py
weaver/models/__init__.py
weaver/routers/__init__.py
weaver/routers/download.py
weaver/routers/search.py
weaver/routers/upload.py
weaver/utils/__init__.py
weaver/utils/auth.py
weaver/utils/db.py
weaver/utils/embeddings.py
textweaver-0.3.115.dist-info/METADATA
textweaver-0.3.115.dist-info/WHEEL
textweaver-0.3.115.dist-info/entry_points.txt
textweaver-0.3.115.dist-info/top_level.txt
textweaver-0.3.115.dist-info/RECORD
