Metadata-Version: 2.1
Name: textweaver
Version: 0.3.115
Summary: A FastAPI-based web server for working with LLMs, embedding models, and Pinecone Vector DB.
Home-page: https://github.com/TrainGRC/textweaver
Author: Wes Ladd
Author-email: wesladd@traingrc.com
License: MIT
Keywords: textweaver,NLP,text-processing,machine-learning
Classifier: Development Status :: 3 - Alpha
Classifier: Intended Audience :: Developers
Classifier: License :: OSI Approved :: MIT License
Classifier: Programming Language :: Python :: 3
Classifier: Programming Language :: Python :: 3.9
Requires-Python: >=3.9
Requires-Dist: fastapi
Requires-Dist: uvicorn
Requires-Dist: gunicorn
Requires-Dist: ksuid
Requires-Dist: pydantic
Requires-Dist: numpy
Requires-Dist: nltk
Requires-Dist: transformers
Requires-Dist: termcolor
Requires-Dist: sentence-transformers
Requires-Dist: starlette
Requires-Dist: python-multipart
Requires-Dist: whisper-ai
Requires-Dist: moviepy
Requires-Dist: mutagen
Requires-Dist: PyPDF2
Requires-Dist: uvloop
Requires-Dist: boto3
Requires-Dist: pydub
Requires-Dist: jwt
Requires-Dist: python-jose
Requires-Dist: pinecone-client
Requires-Dist: python-dotenv
Requires-Dist: pdf2image
Requires-Dist: python-magic
Requires-Dist: httpx
